[
    {
        "name": "Alvian Cahyo Pambudi",
        "nrp": "002138414",
        "email": "alviancahyopambudi@gmail.com"
    },
    {
        "name": "Konatsu HIguchi",
        "nrp": "002343493",
        "email": "higuchikonatsu@gmail.com"
    },
    {
        "name": "Adellya Dwi Anugrah",
        "nrp": "032423409",
        "email": "adellyadwianugrah@gmail.com"
    },
    {
        "name": "Dewi Kumala Putri Firdaus",
        "nrp": "00923473",
        "email": "dewikumalaputrifirdaus@gmail.com"
    }
]